autoboot_data/__init__.py
autoboot_data/autoboot-data-redis.schema.json
autoboot_data/redis/__init__.py
autoboot_data/redis/queue.py
autoboot_data/redis/redis_config.py
autoboot_data/redis/redis_properties.py
autoboot_data-0.5.0.dist-info/LICENSE.txt
autoboot_data-0.5.0.dist-info/METADATA
autoboot_data-0.5.0.dist-info/WHEEL
autoboot_data-0.5.0.dist-info/top_level.txt
autoboot_data-0.5.0.dist-info/RECORD
