Metadata-Version: 2.1
Name: autoboot-data
Version: 0.5.0
Summary: Data access build with autoboot
Home-page: https://github.com/yizzuide/autoboot_data
Author: yizzuide
Author-email: fu837014586@163.com
License: MIT
Keywords: autoboot,data,redis
Classifier: Development Status :: 5 - Production/Stable
Classifier: Operating System :: OS Independent
Classifier: Intended Audience :: Developers
Classifier: Programming Language :: Python :: 3.8
Classifier: License :: OSI Approved :: MIT License
Requires-Python: >=3.8
License-File: LICENSE.txt
Requires-Dist: autoboot <1.0,>=0.10.0
Provides-Extra: redis
Requires-Dist: redis >=4.0.0 ; extra == 'redis'
